stylecolor/__init__.py
stylecolor/__init__.pyi
stylecolor/ansi_styles.py
stylecolor/example.py
stylecolor/format.py
stylecolor-1.0.4.dist-info/LICENSE
stylecolor-1.0.4.dist-info/METADATA
stylecolor-1.0.4.dist-info/WHEEL
stylecolor-1.0.4.dist-info/top_level.txt
stylecolor-1.0.4.dist-info/RECORD
