Metadata-Version: 2.1
Name: stylecolor
Version: 1.0.4
Summary: The simplest package to apply style and color in terminal
Author-email: Clovis P <clovisp.pypi@gmail.com>
Project-URL: Homepage, https://github.com/CloClo0/stylecolor
Keywords: style,color,ANSI,shell,terminal,text,colorama,termcolor
Classifier: Programming Language :: Python :: 3
Classifier: License :: OSI Approved :: MIT License
Classifier: Operating System :: OS Independent
Classifier: Topic :: Utilities
Classifier: Topic :: System :: Shells
Classifier: Topic :: Text Processing
Classifier: Environment :: Console
Requires-Python: >=3.2
License-File: LICENSE
